BrowserPOM/__init__.py
BrowserPOM/decorator.py
BrowserPOM/pageobject.py
BrowserPOM/pom_stubs.py
BrowserPOM/uiobject.py
BrowserPOM/addons/playwright_page_method.js
robotframework_browserpom-0.5.0.dist-info/METADATA
robotframework_browserpom-0.5.0.dist-info/WHEEL
robotframework_browserpom-0.5.0.dist-info/licenses/LICENSE
robotframework_browserpom-0.5.0.dist-info/RECORD
