Metadata-Version: 2.4
Name: robotframework-browserpom
Version: 0.5.0
Summary: robotframework-browser library extension to create Page Objects
Author-email: Hasan Alp Zengin <hasanalpzengin@gmail.com>
License-File: LICENSE
Classifier: Framework :: Robot Framework
Classifier: Framework :: Robot Framework :: Library
Classifier: Framework :: Robot Framework :: Tool
Classifier: License :: OSI Approved :: MIT License
Classifier: Operating System :: OS Independent
Classifier: Programming Language :: Python :: 3
Classifier: Topic :: Software Development :: Quality Assurance
Classifier: Topic :: Software Development :: Testing
Requires-Python: <4.0,>=3.9
Requires-Dist: robotframework-browser
Requires-Dist: robotframework>=5.1.0
